qfp/__init__.py
qfp/audio.py
qfp/db.py
qfp/fingerprint.py
qfp/quads.py
qfp/utils.py
qfp-0.2.0.dist-info/WHEEL
qfp-0.2.0.dist-info/METADATA
qfp-0.2.0.dist-info/RECORD
