Metadata-Version: 2.1
Name: qfp
Version: 0.2.0
Summary: Quad-based audio fingerprinting (fork of https://github.com/mbortnyck/qfp)
Home-page: https://github.com/SuperSonicHub1/qfp
Keywords: audio,fingerprinting
Author: Michael Bortnyck
Author-email: michael.bortnyck@gmail.com
Maintainer: Kyle Anthony Williams
Maintainer-email: kyle.anthony.williams2@gmail.com
Requires-Python: >=3.8,<3.11
Classifier: Programming Language :: Python :: 3
Classifier: Programming Language :: Python :: 3.10
Classifier: Programming Language :: Python :: 3.8
Classifier: Programming Language :: Python :: 3.9
Classifier: Topic :: Multimedia :: Sound/Audio :: Analysis
Requires-Dist: bitstring (>=3.1.9,<4.0.0)
Requires-Dist: numpy (>=1.22.1,<2.0.0)
Requires-Dist: pydub (>=0.25.1,<0.26.0)
Requires-Dist: scipy (>=1.7.3,<2.0.0)
Project-URL: Documentation, https://github.com/SuperSonicHub1/qfp#readme
Project-URL: Repository, https://github.com/SuperSonicHub1/qfp
